{"assets":{"A12C450418D1965E7210CBFB08F69F8B":{"type":"texture","index":1,"assetRequest":{"type":"slide","state":"contents","slide":"none"},"url":{"native":"assets\/672E81FD-E505-47FE-9E29-9575CDAD5287.pdf"},"width":1024,"height":768},"C7FE8E6C315DBA7F6F20578C84A1AADB":{"type":"texture","index":0,"assetRequest":{"type":"slide","state":"contents","slide":"none"},"url":{"native":"assets\/672E81FD-E505-47FE-9E29-9575CDAD5287.pdf"},"width":1024,"height":768}},"events":[{"effects":[{"beginTime":0,"baseLayer":{"animations":[],"initialState":{"affineTransform":[1,0,0,1,0,0],"masksToBounds":false,"rotation":0,"scale":1,"position":{"pointX":512,"pointY":384},"width":1024,"sublayerTransform":[1,0,0,0,0,1,0,0,0,0,1,0,0,0,0,1],"contentsRect":{"y":0,"x":0,"width":1,"height":1},"opacity":1,"edgeAntialiasingMask":251658240,"height":768,"hidden":false,"anchorPoint":{"pointX":0.5,"pointY":0.5}},"objectID":"0","layers":[{"animations":[],"initialState":{"affineTransform":[1,0,0,1,0,0],"masksToBounds":false,"rotation":0,"scale":1,"position":{"pointX":512,"pointY":384},"width":1024,"sublayerTransform":[1,0,0,0,0,1,0,0,0,0,1,-0.00049229876906403734,0,0,0,1],"contentsRect":{"y":0,"x":0,"width":1,"height":1},"opacity":1,"edgeAntialiasingMask":251658240,"height":768,"hidden":false,"anchorPoint":{"pointX":0.5,"pointY":0.5}},"layers":[{"animations":[],"layers":[],"texturedRectangle":{"isBackgroundTexture":false,"singleTextureOpacity":1,"textureType":0,"textBaseline":0,"textXHeight":0,"isVerticalText":false},"initialState":{"affineTransform":[1,0,0,1,0,0],"masksToBounds":false,"rotation":0,"scale":1,"position":{"pointX":512,"pointY":384},"width":1024,"sublayerTransform":[1,0,0,0,0,1,0,0,0,0,1,0,0,0,0,1],"contentsRect":{"y":0,"x":0,"width":1,"height":1},"opacity":1,"edgeAntialiasingMask":0,"height":768,"hidden":false,"anchorPoint":{"pointX":0.5,"pointY":0.5}},"texture":"A12C450418D1965E7210CBFB08F69F8B"},{"animations":[{"timeOffset":0,"from":{"scalar":false},"beginTime":0,"repeatCount":0,"fillMode":"both","property":"hidden","autoreverses":false,"duration":0.01,"to":{"scalar":true}}],"layers":[],"texturedRectangle":{"isBackgroundTexture":false,"singleTextureOpacity":1,"textureType":0,"textBaseline":0,"textXHeight":0,"isVerticalText":false},"initialState":{"affineTransform":[1,0,0,1,0,0],"masksToBounds":false,"rotation":0,"scale":1,"position":{"pointX":512,"pointY":384},"width":1024,"sublayerTransform":[1,0,0,0,0,1,0,0,0,0,1,0,0,0,0,1],"contentsRect":{"y":0,"x":0,"width":1,"height":1},"opacity":1,"edgeAntialiasingMask":0,"height":768,"hidden":false,"anchorPoint":{"pointX":0.5,"pointY":0.5}},"texture":"C7FE8E6C315DBA7F6F20578C84A1AADB"}]}]},"effects":[],"duration":0.01,"type":"transition","name":"none","objectID":"0"}],"automaticPlay":false,"hyperlinks":[],"accessibility":[{"text":"Our model with the fixed effects (as well as the random effects) is a better fit for our data than is the model just with the random effects.  Now we need to look at the model parameters using the summary() function…","targetRectangle":{"y":424.81204223632812,"x":123.68359756469727,"width":841.015625,"height":146.234375}},{"text":"> anova(model.full, model.null)","targetRectangle":{"y":48.000003337860107,"x":25.420919418334961,"width":372.060546875,"height":23}},{"text":"refitting model(s) with ML (instead of REML)","targetRectangle":{"y":71.000003337860107,"x":25.420919418334961,"width":528.0859375,"height":23}},{"text":"Data: DV","targetRectangle":{"y":94.000003337860107,"x":25.420919418334961,"width":96.015625,"height":23}},{"text":"Models:","targetRectangle":{"y":117.00000333786011,"x":25.420919418334961,"width":84.013671875,"height":23}},{"text":"model.null: RT ~ (1 + Context * Sentence | Subject) + (1 + Context * Sentence | ","targetRectangle":{"y":140.00000333786011,"x":25.420919418334961,"width":960.15625,"height":23}},{"text":"model.null:     Item)","targetRectangle":{"y":163.00000333786011,"x":25.420919418334961,"width":252.041015625,"height":23}},{"text":"model.full: RT ~ Context * Sentence + (1 + Context * Sentence | Subject) + ","targetRectangle":{"y":186.00000333786011,"x":25.420919418334961,"width":900.146484375,"height":23}},{"text":"model.full:     (1 + Context * Sentence | Item)","targetRectangle":{"y":209.00000333786011,"x":25.420919418334961,"width":564.091796875,"height":23}},{"text":"           Df   AIC   BIC logLik deviance  Chisq Chi Df Pr(>Chisq)  ","targetRectangle":{"y":232.00000333786011,"x":25.420919418334961,"width":816.1328125,"height":23}},{"text":"model.null 22 26720 26840 -13338    26676                           ","targetRectangle":{"y":255.00000333786011,"x":25.420919418334961,"width":816.1328125,"height":23}},{"text":"model.full 25 26718 26853 -13334    26668 8.6625      3    0.03413 *","targetRectangle":{"y":278.00000333786011,"x":25.420919418334961,"width":816.1328125,"height":23}},{"text":"---","targetRectangle":{"y":301.00000333786011,"x":25.420919418334961,"width":36.005859375,"height":23}},{"text":"Signif. codes:  0 ‘***’ 0.001 ‘**’ 0.01 ‘*’ 0.05 ‘.’ 0.1 ‘ ’ 1","targetRectangle":{"y":324.00000333786011,"x":25.420919418334961,"width":744.12109375,"height":23}},{"text":"> summary(model_full)","targetRectangle":{"y":612.00000071525574,"x":150.77587890625,"width":352.857421875,"height":31}}],"baseLayer":{"animations":[],"initialState":{"affineTransform":[1,0,0,1,0,0],"masksToBounds":false,"rotation":0,"scale":1,"position":{"pointX":512,"pointY":384},"width":1024,"sublayerTransform":[1,0,0,0,0,1,0,0,0,0,1,0,0,0,0,1],"contentsRect":{"y":0,"x":0,"width":1,"height":1},"opacity":1,"edgeAntialiasingMask":251658240,"height":768,"hidden":false,"anchorPoint":{"pointX":0.5,"pointY":0.5}},"objectID":"0","layers":[{"animations":[],"initialState":{"affineTransform":[1,0,0,1,0,0],"masksToBounds":false,"rotation":0,"scale":1,"position":{"pointX":512,"pointY":384},"width":1024,"sublayerTransform":[1,0,0,0,0,1,0,0,0,0,1,-0.00049229876906403734,0,0,0,1],"contentsRect":{"y":0,"x":0,"width":1,"height":1},"opacity":1,"edgeAntialiasingMask":251658240,"height":768,"hidden":false,"anchorPoint":{"pointX":0.5,"pointY":0.5}},"layers":[{"animations":[],"layers":[],"texturedRectangle":{"isBackgroundTexture":false,"singleTextureOpacity":1,"textureType":0,"textBaseline":0,"textXHeight":0,"isVerticalText":false},"initialState":{"affineTransform":[1,0,0,1,0,0],"masksToBounds":false,"rotation":0,"scale":1,"position":{"pointX":512,"pointY":384},"width":1024,"sublayerTransform":[1,0,0,0,0,1,0,0,0,0,1,0,0,0,0,1],"contentsRect":{"y":0,"x":0,"width":1,"height":1},"opacity":1,"edgeAntialiasingMask":0,"height":768,"hidden":false,"anchorPoint":{"pointX":0.5,"pointY":0.5}},"texture":"C7FE8E6C315DBA7F6F20578C84A1AADB"}]}]}}]}